<?xml version="1.0" encoding="UTF-8"?>

<!-- For a complete description of what action steps are built-in, and
     what formats the definitions of systems should take, see the file
     "../ucpsystems.xsd".  
-->

<systems> 

   <system id="pronominalization.pronoun" region="PRONOMINALIZATION" metafunction="ideational">
	<chooser id="c-pronominalization.pronoun"/>
      <conditions>
          <condition features="@type:entity @feat:Salient:true"/>
      </conditions>
      <actions>
	  <action choice="pronoun-it">
		<add-proposition propositions="@it" />
		<add-feature feature="Num" value="sg"/>
	  </action>

	  <action choice="pronoun-this">
		<add-proposition propositions="@context" />
		<add-feature feature="Proximity" value="proximal"/>
		<add-feature feature="Delimitation" value="unique"/>
	  </action>

	  <action choice="pronoun-that">
		<add-proposition propositions="@context" />
		<add-feature feature="Proximity" value="distal"/>
		<add-feature feature="Delimitation" value="unique"/>
	  </action>
    </actions>
   </system>

</systems>
